ori_optimize_linux/__init__.py
ori_optimize_linux/envs/__init__.py
ori_optimize_linux/envs/ori_optimize_linux.py
ori_optimize_linux-0.0.7.dist-info/METADATA
ori_optimize_linux-0.0.7.dist-info/WHEEL
ori_optimize_linux-0.0.7.dist-info/top_level.txt
ori_optimize_linux-0.0.7.dist-info/RECORD
