Metadata-Version: 2.1
Name: ori-optimize-linux
Version: 0.0.7
Summary: a environment that controls STL model rotate to reach the maximal 3D printing quality.
Requires-Dist: gym (==0.25.2)
Requires-Dist: numpy
